azureml_inference_server_http/__init__.py
azureml_inference_server_http/__main__.py
azureml_inference_server_http/_version.py
azureml_inference_server_http/amlserver.py
azureml_inference_server_http/amlserver_linux.py
azureml_inference_server_http/amlserver_win.py
azureml_inference_server_http/args.py
azureml_inference_server_http/constants.py
azureml_inference_server_http/log_config.py
azureml_inference_server_http/logging.json
azureml_inference_server_http/print_log_hook.py
azureml_inference_server_http/api/__init__.py
azureml_inference_server_http/api/aml_request.py
azureml_inference_server_http/api/aml_response.py
azureml_inference_server_http/server/__init__.py
azureml_inference_server_http/server/aml_blueprint.py
azureml_inference_server_http/server/appinsights_client.py
azureml_inference_server_http/server/config.py
azureml_inference_server_http/server/create_app.py
azureml_inference_server_http/server/entry.py
azureml_inference_server_http/server/exceptions.py
azureml_inference_server_http/server/input_parsers.py
azureml_inference_server_http/server/routes.py
azureml_inference_server_http/server/swagger.py
azureml_inference_server_http/server/swagger2_template.json
azureml_inference_server_http/server/swagger3_template.json
azureml_inference_server_http/server/user_script.py
azureml_inference_server_http/server/utils.py
azureml_inference_server_http-1.5.1.dist-info/licenses/LICENSE
azureml_inference_server_http-1.5.1.dist-info/METADATA
azureml_inference_server_http-1.5.1.dist-info/WHEEL
azureml_inference_server_http-1.5.1.dist-info/entry_points.txt
azureml_inference_server_http-1.5.1.dist-info/top_level.txt
azureml_inference_server_http-1.5.1.dist-info/RECORD
