Metadata-Version: 2.4
Name: azureml-inference-server-http
Version: 1.5.1
Summary: Azure Machine Learning inferencing server.
Author: Microsoft Corp
Author-email: amlInferenceImages@microsoft.com
License: https://aka.ms/azureml-sdk-license
Classifier: Programming Language :: Python
Classifier: Programming Language :: Python :: 3
Classifier: Programming Language :: Python :: 3.9
Classifier: Programming Language :: Python :: 3.10
Classifier: Programming Language :: Python :: 3.11
Classifier: Programming Language :: Python :: 3.12
Classifier: Intended Audience :: Developers
Classifier: Intended Audience :: Science/Research
Classifier: License :: Other/Proprietary License
Classifier: Operating System :: Microsoft :: Windows
Classifier: Operating System :: MacOS
Classifier: Operating System :: POSIX :: Linux
Requires-Python: >=3.9
License-File: LICENSE
Requires-Dist: flask~=3.1.0
Requires-Dist: flask-cors~=6.0.0
Requires-Dist: gunicorn>=23.0.0; platform_system != "Windows"
Requires-Dist: inference-schema~=1.8.0
Requires-Dist: opentelemetry-sdk==1.33.0
Requires-Dist: opentelemetry-api==1.33.0
Requires-Dist: opentelemetry-semantic-conventions
Requires-Dist: azure-monitor-opentelemetry-exporter
Requires-Dist: psutil<6.0.0; platform_system == "Windows"
Requires-Dist: pydantic~=2.12.0
Requires-Dist: pydantic-settings
Requires-Dist: waitress>=3.0.1; platform_system == "Windows"
Requires-Dist: werkzeug>=3.0.3
Requires-Dist: certifi>=2024.7.4
Provides-Extra: dev
Requires-Dist: azure-monitor-query; extra == "dev"
Requires-Dist: black; extra == "dev"
Requires-Dist: coverage; extra == "dev"
Requires-Dist: debugpy; extra == "dev"
Requires-Dist: flake8; extra == "dev"
Requires-Dist: flake8-comprehensions; extra == "dev"
Requires-Dist: flake8-import-order; extra == "dev"
Requires-Dist: junitparser==2.0.0; extra == "dev"
Requires-Dist: numpy; extra == "dev"
Requires-Dist: pandas; extra == "dev"
Requires-Dist: pre-commit; extra == "dev"
Requires-Dist: pytest; extra == "dev"
Requires-Dist: pytest-asyncio; extra == "dev"
Requires-Dist: pytest-benchmark; extra == "dev"
Requires-Dist: pytest-cov; extra == "dev"
Requires-Dist: requests; extra == "dev"
Requires-Dist: towncrier==21.9.0; extra == "dev"
Requires-Dist: wheel; extra == "dev"
Dynamic: author
Dynamic: author-email
Dynamic: classifier
Dynamic: description
Dynamic: description-content-type
Dynamic: license
Dynamic: license-file
Dynamic: provides-extra
Dynamic: requires-dist
Dynamic: requires-python
Dynamic: summary
